durabledict
