Metadata-Version: 1.0
Name: durabledict
Version: 0.9.1
Summary: Dictionary-style access to different types of models.
Home-page: http://github.com/disqus/durabledict/
Author: DISQUS
Author-email: opensource@disqus.com
License: UNKNOWN
Platform: UNKNOWN
Classifier: Intended Audience :: Developers
Classifier: Intended Audience :: System Administrators
Classifier: Operating System :: OS Independent
Classifier: Topic :: Software Development
